{
  "accentColor": "{{appsmith.theme.colors.primaryColor}}",
  "animateLoading": true,
  "borderColor": "#E0DEDE",
  "borderRadius": "{{appsmith.theme.borderRadius.appBorderRadius}}",
  "borderWidth": "1",
  "bottomRow": 244,
  "boxShadow": "{{appsmith.theme.boxShadow.appBoxShadow}}",
  "cachedTableData": {},
  "canFreezeColumn": true,
  "childStylesheet": {
    "button": {
      "borderRadius": "{{appsmith.theme.borderRadius.appBorderRadius}}",
      "boxShadow": "none",
      "buttonColor": "{{appsmith.theme.colors.primaryColor}}"
    },
    "editActions": {
      "discardBorderRadius": "{{appsmith.theme.borderRadius.appBorderRadius}}",
      "discardButtonColor": "{{appsmith.theme.colors.primaryColor}}",
      "saveBorderRadius": "{{appsmith.theme.borderRadius.appBorderRadius}}",
      "saveButtonColor": "{{appsmith.theme.colors.primaryColor}}"
    },
    "iconButton": {
      "borderRadius": "{{appsmith.theme.borderRadius.appBorderRadius}}",
      "boxShadow": "none",
      "buttonColor": "{{appsmith.theme.colors.primaryColor}}"
    },
    "menuButton": {
      "borderRadius": "{{appsmith.theme.borderRadius.appBorderRadius}}",
      "boxShadow": "none",
      "menuColor": "{{appsmith.theme.colors.primaryColor}}"
    }
  },
  "columnOrder": [
    "xn__M_vt_liu____87a4520hska8871go3pbu4tne3a",
    "xn__Tn_Vt_Liu____oeb3877hjlaw783e2lmc3g6bf53a",
    "xn__n_V____22a47i616odn0fljj",
    "xn__Khu_vc____zv7d9665cxwlf4kv18a",
    "xn__S_D_Thng_Trc____sjb926aja4872ldga7968g6f9bfgycyl3g",
    "xn__Nhp_thng_ny____pgbl5870k51wivl0bdm9auva",
    "xn__Xut_thng_ny____pgbl9460kwdziz9xbdm9auva",
    "xn__S_D_Cui_Thng____wjb526a784qga42012agkybvwa8564b",
    "EditActions1"
  ],
  "columnUpdatedAt": 1781256747283,
  "columnWidthMap": {},
  "customIsLoading": false,
  "customIsLoadingValue": "",
  "defaultPageSize": 0,
  "defaultSelectedRowIndex": 0,
  "defaultSelectedRowIndices": [
    0
  ],
  "delimiter": ",",
  "dynamicBindingPathList": [
    {
      "key": "accentColor"
    },
    {
      "key": "borderRadius"
    },
    {
      "key": "boxShadow"
    },
    {
      "key": "tableData"
    },
    {
      "key": "primaryColumns.xn__M_vt_liu____87a4520hska8871go3pbu4tne3a.computedValue"
    },
    {
      "key": "primaryColumns.xn__Tn_Vt_Liu____oeb3877hjlaw783e2lmc3g6bf53a.computedValue"
    },
    {
      "key": "primaryColumns.xn__n_V____22a47i616odn0fljj.computedValue"
    },
    {
      "key": "primaryColumns.xn__Khu_vc____zv7d9665cxwlf4kv18a.computedValue"
    },
    {
      "key": "primaryColumns.xn__S_D_Thng_Trc____sjb926aja4872ldga7968g6f9bfgycyl3g.computedValue"
    },
    {
      "key": "primaryColumns.xn__Nhp_thng_ny____pgbl5870k51wivl0bdm9auva.computedValue"
    },
    {
      "key": "primaryColumns.xn__Xut_thng_ny____pgbl9460kwdziz9xbdm9auva.computedValue"
    },
    {
      "key": "primaryColumns.xn__S_D_Cui_Thng____wjb526a784qga42012agkybvwa8564b.computedValue"
    },
    {
      "key": "primaryColumns.EditActions1.saveButtonColor"
    },
    {
      "key": "primaryColumns.EditActions1.saveBorderRadius"
    },
    {
      "key": "primaryColumns.EditActions1.discardBorderRadius"
    },
    {
      "key": "primaryColumns.EditActions1.isSaveDisabled"
    },
    {
      "key": "primaryColumns.EditActions1.isDiscardDisabled"
    }
  ],
  "dynamicPropertyPathList": [
    {
      "key": "tableData"
    },
    {
      "key": "primaryColumns.EditActions1.isSaveDisabled"
    },
    {
      "key": "primaryColumns.EditActions1.isDiscardDisabled"
    }
  ],
  "dynamicTriggerPathList": [],
  "enableClientSideSearch": true,
  "endOfData": false,
  "flexVerticalAlignment": "start",
  "horizontalAlignment": "LEFT",
  "inlineEditingSaveOption": "ROW_LEVEL",
  "isLoading": false,
  "isSortable": true,
  "isVisible": true,
  "isVisibleDownload": true,
  "isVisibleFilters": false,
  "isVisiblePagination": true,
  "isVisibleSearch": true,
  "key": "v9tt9vk822",
  "label": "Data",
  "leftColumn": 0,
  "minWidth": 450,
  "mobileBottomRow": 208,
  "mobileLeftColumn": 0,
  "mobileRightColumn": 11,
  "mobileTopRow": 180,
  "needsErrorInfo": false,
  "originalBottomRow": 244,
  "originalTopRow": 200,
  "parentColumnSpace": 16.734375,
  "parentId": "0",
  "parentRowSpace": 10,
  "primaryColumnId": "xn__M_vt_liu____87a4520hska8871go3pbu4tne3a",
  "primaryColumns": {
    "EditActions1": {
      "alias": "EditActions1",
      "allowCellWrapping": false,
      "allowSameOptionsInNewRow": true,
      "buttonStyle": "rgb(3, 179, 101)",
      "columnType": "editActions",
      "computedValue": "",
      "currencyCode": "USD",
      "decimals": 0,
      "discardActionLabel": "Discard",
      "discardBorderRadius": "{{Kiem_Ke_Cong_Cu.processedTableData.map((currentRow, currentIndex) => ( (appsmith.theme.borderRadius.appBorderRadius)))}}",
      "discardButtonColor": "#F22B2B",
      "discardButtonVariant": "TERTIARY",
      "discardIconAlign": "left",
      "enableFilter": true,
      "enableSort": true,
      "id": "EditActions1",
      "index": 10,
      "isCellEditable": false,
      "isCellVisible": true,
      "isDerived": true,
      "isDisabled": false,
      "isDiscardDisabled": "{{Kiem_Ke_Cong_Cu.processedTableData.map((currentRow, currentIndex) => ( !Kiem_Ke_Cong_Cu.updatedRowIndices.includes(currentIndex)))}}",
      "isDiscardVisible": true,
      "isEditable": false,
      "isSaveDisabled": "{{Kiem_Ke_Cong_Cu.processedTableData.map((currentRow, currentIndex) => ( !Kiem_Ke_Cong_Cu.updatedRowIndices.includes(currentIndex)))}}",
      "isSaveVisible": true,
      "isVisible": false,
      "label": "Save / Discard",
      "notation": "standard",
      "originalId": "EditActions1",
      "saveActionLabel": "Save",
      "saveBorderRadius": "{{Kiem_Ke_Cong_Cu.processedTableData.map((currentRow, currentIndex) => ( (appsmith.theme.borderRadius.appBorderRadius)))}}",
      "saveButtonColor": "{{Kiem_Ke_Cong_Cu.processedTableData.map((currentRow, currentIndex) => ( (appsmith.theme.colors.primaryColor)))}}",
      "saveIconAlign": "left",
      "sticky": "right",
      "thousandSeparator": true,
      "validation": {},
      "width": 150
    },
    "xn__Khu_vc____zv7d9665cxwlf4kv18a": {
      "alias": "Khu vực / 存放区域",
      "allowCellWrapping": false,
      "allowSameOptionsInNewRow": true,
      "columnType": "text",
      "computedValue": "{{(() => { const tableData = Kiem_Ke_Cong_Cu.processedTableData || []; return tableData.length > 0 ? tableData.map((currentRow, currentIndex) => (currentRow[\"Khu vực / 存放区域\"])) : Khu vực / 存放区域 })()}}",
      "currencyCode": "USD",
      "decimals": 0,
      "enableFilter": true,
      "enableSort": true,
      "horizontalAlignment": "LEFT",
      "id": "xn__Khu_vc____zv7d9665cxwlf4kv18a",
      "index": 4,
      "isCellEditable": false,
      "isCellVisible": true,
      "isDerived": false,
      "isDisabled": false,
      "isDiscardVisible": true,
      "isEditable": false,
      "isSaveVisible": true,
      "isVisible": true,
      "label": "Khu vực / 存放区域",
      "notation": "standard",
      "originalId": "Khu vực / 存放区域",
      "sticky": "",
      "textSize": "0.875rem",
      "thousandSeparator": true,
      "validation": {},
      "verticalAlignment": "CENTER",
      "width": 150
    },
    "xn__M_vt_liu____87a4520hska8871go3pbu4tne3a": {
      "alias": "Mã vật liệu / 物料编码",
      "allowCellWrapping": false,
      "allowSameOptionsInNewRow": true,
      "columnType": "text",
      "computedValue": "{{(() => { const tableData = Kiem_Ke_Cong_Cu.processedTableData || []; return tableData.length > 0 ? tableData.map((currentRow, currentIndex) => (currentRow[\"Mã vật liệu / 物料编码\"])) : Mã vật liệu / 物料编码 })()}}",
      "currencyCode": "USD",
      "decimals": 0,
      "enableFilter": true,
      "enableSort": true,
      "horizontalAlignment": "LEFT",
      "id": "xn__M_vt_liu____87a4520hska8871go3pbu4tne3a",
      "index": 0,
      "isCellEditable": false,
      "isCellVisible": true,
      "isDerived": false,
      "isDisabled": false,
      "isDiscardVisible": true,
      "isEditable": false,
      "isSaveVisible": true,
      "isVisible": true,
      "label": "Mã vật liệu / 物料编码",
      "notation": "standard",
      "originalId": "Mã vật liệu / 物料编码",
      "sticky": "",
      "textSize": "0.875rem",
      "thousandSeparator": true,
      "validation": {},
      "verticalAlignment": "CENTER",
      "width": 150
    },
    "xn__Nhp_thng_ny____pgbl5870k51wivl0bdm9auva": {
      "alias": "Nhập tháng này / 本月入库",
      "allowCellWrapping": false,
      "allowSameOptionsInNewRow": true,
      "columnType": "number",
      "computedValue": "{{(() => { const tableData = Kiem_Ke_Cong_Cu.processedTableData || []; return tableData.length > 0 ? tableData.map((currentRow, currentIndex) => (currentRow[\"Nhập tháng này / 本月入库\"])) : Nhập tháng này / 本月入库 })()}}",
      "currencyCode": "USD",
      "decimals": 0,
      "enableFilter": true,
      "enableSort": true,
      "horizontalAlignment": "LEFT",
      "id": "xn__Nhp_thng_ny____pgbl5870k51wivl0bdm9auva",
      "index": 6,
      "isCellEditable": false,
      "isCellVisible": true,
      "isDerived": false,
      "isDisabled": false,
      "isDiscardVisible": true,
      "isEditable": false,
      "isSaveVisible": true,
      "isVisible": true,
      "label": "Nhập tháng này / 本月入库",
      "notation": "standard",
      "originalId": "Nhập tháng này / 本月入库",
      "sticky": "",
      "textSize": "0.875rem",
      "thousandSeparator": true,
      "validation": {},
      "verticalAlignment": "CENTER",
      "width": 150
    },
    "xn__S_D_Cui_Thng____wjb526a784qga42012agkybvwa8564b": {
      "alias": "Số Dư Cuối Tháng / 本月结存",
      "allowCellWrapping": false,
      "allowSameOptionsInNewRow": true,
      "columnType": "number",
      "computedValue": "{{(() => { const tableData = Kiem_Ke_Cong_Cu.processedTableData || []; return tableData.length > 0 ? tableData.map((currentRow, currentIndex) => (currentRow[\"Số Dư Cuối Tháng / 本月结存\"])) : Số Dư Cuối Tháng / 本月结存 })()}}",
      "currencyCode": "USD",
      "decimals": 0,
      "enableFilter": true,
      "enableSort": true,
      "horizontalAlignment": "LEFT",
      "id": "xn__S_D_Cui_Thng____wjb526a784qga42012agkybvwa8564b",
      "index": 9,
      "isCellEditable": false,
      "isCellVisible": true,
      "isDerived": false,
      "isDisabled": false,
      "isDiscardVisible": true,
      "isEditable": false,
      "isSaveVisible": true,
      "isVisible": true,
      "label": "Số Dư Cuối Tháng / 本月结存",
      "notation": "standard",
      "originalId": "Số Dư Cuối Tháng / 本月结存",
      "sticky": "",
      "textSize": "0.875rem",
      "thousandSeparator": true,
      "validation": {},
      "verticalAlignment": "CENTER",
      "width": 150
    },
    "xn__S_D_Thng_Trc____sjb926aja4872ldga7968g6f9bfgycyl3g": {
      "alias": "Số Dư Tháng Trước / 上月结存",
      "allowCellWrapping": false,
      "allowSameOptionsInNewRow": true,
      "columnType": "number",
      "computedValue": "{{(() => { const tableData = Kiem_Ke_Cong_Cu.processedTableData || []; return tableData.length > 0 ? tableData.map((currentRow, currentIndex) => (currentRow[\"Số Dư Tháng Trước / 上月结存\"])) : Số Dư Tháng Trước / 上月结存 })()}}",
      "currencyCode": "USD",
      "decimals": 0,
      "enableFilter": true,
      "enableSort": true,
      "horizontalAlignment": "LEFT",
      "id": "xn__S_D_Thng_Trc____sjb926aja4872ldga7968g6f9bfgycyl3g",
      "index": 5,
      "isCellEditable": false,
      "isCellVisible": true,
      "isDerived": false,
      "isDisabled": false,
      "isDiscardVisible": true,
      "isEditable": false,
      "isSaveVisible": true,
      "isVisible": true,
      "label": "Số Dư Tháng Trước / 上月结存",
      "notation": "standard",
      "originalId": "Số Dư Tháng Trước / 上月结存",
      "sticky": "",
      "textSize": "0.875rem",
      "thousandSeparator": true,
      "validation": {},
      "verticalAlignment": "CENTER",
      "width": 150
    },
    "xn__Tn_Vt_Liu____oeb3877hjlaw783e2lmc3g6bf53a": {
      "alias": "Tên Vật Liệu / 物料名称",
      "allowCellWrapping": false,
      "allowSameOptionsInNewRow": true,
      "columnType": "text",
      "computedValue": "{{(() => { const tableData = Kiem_Ke_Cong_Cu.processedTableData || []; return tableData.length > 0 ? tableData.map((currentRow, currentIndex) => (currentRow[\"Tên Vật Liệu / 物料名称\"])) : Tên Vật Liệu / 物料名称 })()}}",
      "currencyCode": "USD",
      "decimals": 0,
      "enableFilter": true,
      "enableSort": true,
      "horizontalAlignment": "LEFT",
      "id": "xn__Tn_Vt_Liu____oeb3877hjlaw783e2lmc3g6bf53a",
      "index": 1,
      "isCellEditable": false,
      "isCellVisible": true,
      "isDerived": false,
      "isDisabled": false,
      "isDiscardVisible": true,
      "isEditable": false,
      "isSaveVisible": true,
      "isVisible": true,
      "label": "Tên Vật Liệu / 物料名称",
      "notation": "standard",
      "originalId": "Tên Vật Liệu / 物料名称",
      "sticky": "",
      "textSize": "0.875rem",
      "thousandSeparator": true,
      "validation": {},
      "verticalAlignment": "CENTER",
      "width": 150
    },
    "xn__Xut_thng_ny____pgbl9460kwdziz9xbdm9auva": {
      "alias": "Xuất tháng này / 本月出库",
      "allowCellWrapping": false,
      "allowSameOptionsInNewRow": true,
      "columnType": "number",
      "computedValue": "{{(() => { const tableData = Kiem_Ke_Cong_Cu.processedTableData || []; return tableData.length > 0 ? tableData.map((currentRow, currentIndex) => (currentRow[\"Xuất tháng này / 本月出库\"])) : Xuất tháng này / 本月出库 })()}}",
      "currencyCode": "USD",
      "decimals": 0,
      "enableFilter": true,
      "enableSort": true,
      "horizontalAlignment": "LEFT",
      "id": "xn__Xut_thng_ny____pgbl9460kwdziz9xbdm9auva",
      "index": 7,
      "isCellEditable": false,
      "isCellVisible": true,
      "isDerived": false,
      "isDisabled": false,
      "isDiscardVisible": true,
      "isEditable": false,
      "isSaveVisible": true,
      "isVisible": true,
      "label": "Xuất tháng này / 本月出库",
      "notation": "standard",
      "originalId": "Xuất tháng này / 本月出库",
      "sticky": "",
      "textSize": "0.875rem",
      "thousandSeparator": true,
      "validation": {},
      "verticalAlignment": "CENTER",
      "width": 150
    },
    "xn__n_V____22a47i616odn0fljj": {
      "alias": "Đơn Vị / 单位",
      "allowCellWrapping": false,
      "allowSameOptionsInNewRow": true,
      "columnType": "text",
      "computedValue": "{{(() => { const tableData = Kiem_Ke_Cong_Cu.processedTableData || []; return tableData.length > 0 ? tableData.map((currentRow, currentIndex) => (currentRow[\"Đơn Vị / 单位\"])) : Đơn Vị / 单位 })()}}",
      "currencyCode": "USD",
      "decimals": 0,
      "enableFilter": true,
      "enableSort": true,
      "horizontalAlignment": "LEFT",
      "id": "xn__n_V____22a47i616odn0fljj",
      "index": 3,
      "isCellEditable": false,
      "isCellVisible": true,
      "isDerived": false,
      "isDisabled": false,
      "isDiscardVisible": true,
      "isEditable": false,
      "isSaveVisible": true,
      "isVisible": true,
      "label": "Đơn Vị / 单位",
      "notation": "standard",
      "originalId": "Đơn Vị / 单位",
      "sticky": "",
      "textSize": "0.875rem",
      "thousandSeparator": true,
      "validation": {},
      "verticalAlignment": "CENTER",
      "width": 150
    }
  },
  "renderMode": "CANVAS",
  "responsiveBehavior": "fill",
  "rightColumn": 63,
  "searchKey": "",
  "showInlineEditingOptionDropdown": true,
  "tableData": "{{Get_Inventory_Data.data}}",
  "textSize": "0.875rem",
  "topRow": 200,
  "totalRecordsCount": 0,
  "type": "TABLE_WIDGET_V2",
  "version": 2,
  "verticalAlignment": "CENTER",
  "widgetId": "lvbx311qfn",
  "widgetName": "Kiem_Ke_Cong_Cu"
}